{
  "qasimia-crhill-rhwagner-aael-khayal-1985.html": "ok",
  "qiongzhuea-hsueh-f-tpyi.html": "ok",
  "quadraditum-fhcramer-1964.html": "ok",
  "quadraeculina-vsmaljavkina-1949.html": "ok",
  "quadraplanus-brossus.html": "ok",
  "quadrasia-elmer.html": "ok",
  "quadrella-angustifolia.html": "ok",
  "quadrella-antonensis.html": "ok",
  "quadrella-asperifolia.html": "ok",
  "quadrella-calciphila.html": "ok",
  "quadrella-cynophallophora.html": "ok",
  "quadrella-domingensis.html": "ok",
  "quadrella-dressleri.html": "ok",
  "quadrella-ferruginea.html": "ok",
  "quadrella-filipes.html": "ok",
  "quadrella-incana.html": "ok",
  "quadrella-indica.html": "ok",
  "quadrella-isthmensis.html": "ok",
  "quadrella-jpresl.html": "ok",
  "quadrella-lindeniana.html": "ok",
  "quadrella-lundellii.html": "ok",
  "quadrella-mirifica.html": "ok",
  "quadrella-morenoi.html": "ok",
  "quadrella-odoratissima.html": "ok",
  "quadrella-pringlei.html": "ok",
  "quadrella-quintanarooensis.html": "ok",
  "quadrella-singularis.html": "ok",
  "quadrella-steyermarkii.html": "ok",
  "quadribractea-moluccana.html": "ok",
  "quadrichloris-fott-1959.html": "ok",
  "quadricoccus-ellipticus.html": "ok",
  "quadricoccus-euryhalinicus.html": "ok",
  "quadricoccus-fott-1948.html": "ok",
  "quadricoccus-laevis.html": "ok",
  "quadricoccus-verrucosus.html": "ok",
  "quadricolpites-reticulatus.html": "ok",
  "quadrigula-chodatii.html": "ok",
  "quadrigula-closterioides.html": "ok",
  "quadrigula-closteroides.html": "ok",
  "quadrigula-korshikovii.html": "ok",
  "quadrigula-korsikovii.html": "ok",
  "quadrigula-pfitzeri.html": "ok",
  "quadriplatanus-georgianus.html": "ok",
  "quadrispermum-emfriis-krpedersen-prcrane-2013.html": "ok",
  "quadrocladus-kmadler-1957.html": "ok",
  "quaestora-gmapes-gwrothwell-1980.html": "ok",
  "qualea-acuminata.html": "ok",
  "qualea-amapaensis.html": "ok",
  "qualea-amoena.html": "ok",
  "qualea-aubl.html": "ok",
  "qualea-brasiliana.html": "ok",
  "qualea-brevipedicellata.html": "ok",
  "qualea-caerulea.html": "ok",
  "qualea-calophylla.html": "ok",
  "qualea-clavata.html": "ok",
  "qualea-coerulea.html": "ok",
  "qualea-cordata.html": "ok",
  "qualea-cryptantha.html": "ok",
  "qualea-cyanea.html": "ok",
  "qualea-cymulosa.html": "ok",
  "qualea-decorticans.html": "ok",
  "qualea-densiflora.html": "ok",
  "qualea-dinizii.html": "ok",
  "qualea-elegans.html": "ok",
  "qualea-gestasiana.html": "ok",
  "qualea-gracilior.html": "ok",
  "qualea-grandiflora.html": "ok",
  "qualea-hannekesaskiarum.html": "ok",
  "qualea-homosepala.html": "ok",
  "qualea-impexa.html": "ok",
  "qualea-ingens.html": "ok",
  "qualea-insignis.html": "ok",
  "qualea-johannabakkerae.html": "ok",
  "qualea-labouriauana.html": "ok",
  "qualea-lundii.html": "ok",
  "qualea-macropetala.html": "ok",
  "qualea-marioniae.html": "ok",
  "qualea-megalocarpa.html": "ok",
  "qualea-mori-boomii.html": "ok",
  "qualea-muelleriana.html": "ok",
  "qualea-multiflora.html": "ok",
  "qualea-panamensis.html": "ok",
  "qualea-paraensis.html": "ok",
  "qualea-parviflora.html": "ok",
  "qualea-polychroma.html": "ok",
  "qualea-rosea.html": "ok",
  "qualea-rupicola.html": "ok",
  "qualea-schomburgkiana.html": "ok",
  "qualea-selloi.html": "ok",
  "qualea-tessmannii.html": "ok",
  "qualea-themistoclesii.html": "ok",
  "qualea-tricolor.html": "ok",
  "qualea-tuberculata.html": "ok",
  "qualea-wurdackii.html": "ok",
  "qualisaspora-jbrichardson-jhford-fparker-1984.html": "ok",
  "quamoclidion-angulatum.html": "ok",
  "quamoclit-cardinalis.html": "ok",
  "quamoclit-mill.html": "ok",
  "quamoclit-pennata.html": "ok",
  "quamoclit-rodriguesii.html": "ok",
  "quamoclit-sloteri.html": "ok",
  "quamoclita-raf.html": "ok",
  "quapoya-aubl.html": "ok",
  "quapoya-littoralis.html": "ok",
  "quararibea-alversonii.html": "ok",
  "quararibea-amazonica.html": "ok",
  "quararibea-angustifolia.html": "ok",
  "quararibea-aristeguietae.html": "ok",
  "quararibea-asterolepis.html": "ok",
  "quararibea-aubl.html": "ok",
  "quararibea-bilobata.html": "ok",
  "quararibea-cacao.html": "ok",
  "quararibea-caldasiana.html": "ok",
  "quararibea-calycoptera.html": "ok",
  "quararibea-casasecae.html": "ok",
  "quararibea-cogolloi.html": "ok",
  "quararibea-costaricensis.html": "ok",
  "quararibea-cryptantha.html": "ok",
  "quararibea-duckei.html": "ok",
  "quararibea-floribunda.html": "ok",
  "quararibea-foenigraeca.html": "ok",
  "quararibea-funebris.html": "ok",
  "quararibea-gigantiflora.html": "ok",
  "quararibea-glazovii.html": "ok",
  "quararibea-gomeziana.html": "ok",
  "quararibea-grandifolia.html": "ok",
  "quararibea-guatemalteca.html": "ok",
  "quararibea-guianensis.html": "ok",
  "quararibea-magnifica.html": "ok",
  "quararibea-martini.html": "ok",
  "quararibea-mayanum.html": "ok",
  "quararibea-mayarum.html": "ok",
  "quararibea-nigrescens.html": "ok",
  "quararibea-obovalifolia.html": "ok",
  "quararibea-parviflora.html": "ok",
  "quararibea-pendula.html": "ok",
  "quararibea-pendulifera.html": "ok",
  "quararibea-penduliflora.html": "ok",
  "quararibea-platyphylla.html": "ok",
  "quararibea-pterocalyx.html": "ok",
  "quararibea-pumila.html": "ok",
  "quararibea-rangelii.html": "ok",
  "quararibea-reflexipetala.html": "ok",
  "quararibea-ruiziana.html": "ok",
  "quararibea-sessiliflora.html": "ok",
  "quararibea-similis.html": "ok",
  "quararibea-spatulata.html": "ok",
  "quararibea-stenophylla.html": "ok",
  "quararibea-steyermarkii.html": "ok",
  "quararibea-tessmannii.html": "ok",
  "quararibea-tulekunae.html": "ok",
  "quararibea-turbinata.html": "ok",
  "quararibea-velutina.html": "ok",
  "quararibea-villanuevae.html": "ok",
  "quararibea-yunckeri.html": "ok",
  "quartinia-arich.html": "ok",
  "quartinia-endl.html": "ok",
  "quasiantennaria-linearifolia.html": "ok",
  "quasisequoia-vsrinivasan-emfriis-1989.html": "ok",
  "quassia-amara.html": "ok",
  "quassia-arnhemensis.html": "ok",
  "quaternella-confusa.html": "ok",
  "quaternella-ephedroides.html": "ok",
  "quaternella-glabratoides.html": "ok",
  "quechua-glabrescens.html": "ok",
  "quechualia-cardenasii.html": "ok",
  "quechualia-fulta.html": "ok",
  "quechualia-smithii.html": "ok",
  "quechualia-trixioides.html": "ok",
  "quedlinburgia-eknobloch-dhmai-1984.html": "ok",
  "quekettia-jenmanii.html": "ok",
  "quekettia-lindl.html": "ok",
  "quekettia-microscopica.html": "ok",
  "quekettia-papillosa.html": "ok",
  "quekettia-pygmaea.html": "ok",
  "quekettia-theresiae.html": "ok",
  "quekettia-vermeuleniana.html": "ok",
  "quelchia-bracteata.html": "ok",
  "quelchia-cardonae.html": "ok",
  "quelchia-conferta.html": "ok",
  "quelchia-eriocaulis.html": "ok",
  "quelchia-grandifolia.html": "ok",
  "quercifilix-copel.html": "ok",
  "quercinium-knowltoni.html": "ok",
  "quercinium-lamarense.html": "ok",
  "quercinium-unger-1842.html": "ok",
  "quercites-hacberger-1832.html": "ok",
  "quercophyllum-chinkapinense.html": "ok",
  "quercophyllum-fontaine-1889.html": "ok",
  "quercophyllum-grossedentatum.html": "ok",
  "quercophyllum-platanoides.html": "ok",
  "quercophyllum-wyomingense.html": "ok",
  "quercoxylon-ehofmann-1929.html": "ok",
  "quercus-abnormalis.html": "ok",
  "quercus-acatenangensis.html": "ok",
  "quercus-acerifolia.html": "ok",
  "quercus-acrodonta.html": "ok",
  "quercus-aculcingensis.html": "ok",
  "quercus-acuta.html": "ok",
  "quercus-acutidens.html": "ok",
  "quercus-acutifolia.html": "ok",
  "quercus-acutissima.html": "ok",
  "quercus-aerea.html": "ok",
  "quercus-afares.html": "ok",
  "quercus-affinis.html": "ok",
  "quercus-agrifolia.html": "ok",
  "quercus-ajoensis.html": "ok",
  "quercus-alaskana.html": "ok",
  "quercus-alba.html": "ok",
  "quercus-albescens.html": "ok",
  "quercus-albicaulis.html": "ok",
  "quercus-albocincta.html": "ok",
  "quercus-aliena.html": "ok",
  "quercus-alienocrispula.html": "ok",
  "quercus-alienoserratoides.html": "ok",
  "quercus-alnifolia.html": "ok",
  "quercus-alpescens.html": "ok",
  "quercus-alpestris.html": "ok",
  "quercus-alvordiana.html": "ok",
  "quercus-ambigens.html": "ok",
  "quercus-americana.html": "ok",
  "quercus-amherstiana.html": "ok",
  "quercus-amissaeloba.html": "ok",
  "quercus-andegavensis.html": "ok",
  "quercus-andrewsii.html": "ok",
  "quercus-anguste-lepidosa.html": "ok",
  "quercus-anguste-lepidota.html": "ok",
  "quercus-angustiloba.html": "ok",
  "quercus-annulata.html": "ok",
  "quercus-arbutifolia.html": "ok",
  "quercus-arenicola.html": "ok",
  "quercus-argentata.html": "ok",
  "quercus-argyrotricha.html": "ok",
  "quercus-aristata.html": "ok",
  "quercus-arizonica.html": "ok",
  "quercus-arkansana.html": "ok",
  "quercus-arrimatensis.html": "ok",
  "quercus-ashei.html": "ok",
  "quercus-asymmetrica.html": "ok",
  "quercus-atlantica.html": "ok",
  "quercus-aucheri.html": "ok",
  "quercus-audleyensis.html": "ok",
  "quercus-augustini.html": "ok",
  "quercus-aurea.html": "ok",
  "quercus-austrina.html": "ok",
  "quercus-austrocochinchinensis.html": "ok",
  "quercus-auzandrii.html": "ok",
  "quercus-auzendei.html": "ok",
  "quercus-avellaniformis.html": "ok",
  "quercus-baenitzii.html": "ok",
  "quercus-balaninorum.html": "ok",
  "quercus-baloot.html": "ok",
  "quercus-bambusifolia.html": "ok",
  "quercus-baniensis.html": "ok",
  "quercus-banksiaefolia.html": "ok",
  "quercus-baolamensis.html": "ok",
  "quercus-baronii.html": "ok",
  "quercus-barrancana.html": "ok",
  "quercus-basaseachicensis.html": "ok",
  "quercus-bawanglingensis.html": "ok",
  "quercus-beadlei.html": "ok",
  "quercus-bebbiana.html": "ok",
  "quercus-beckyae.html": "ok",
  "quercus-beguinotii.html": "ok",
  "quercus-bella.html": "ok",
  "quercus-benderi.html": "ok",
  "quercus-benthamii.html": "ok",
  "quercus-berberidifolia.html": "ok",
  "quercus-bernardensis.html": "ok",
  "quercus-berryi.html": "ok",
  "quercus-beturica.html": "ok",
  "quercus-bibbiana.html": "ok",
  "quercus-bicolor.html": "ok",
  "quercus-bicornis.html": "ok",
  "quercus-bidoupensis.html": "ok",
  "quercus-bimundorum.html": "ok",
  "quercus-bivoniana.html": "ok",
  "quercus-blakei.html": "ok",
  "quercus-blaoensis.html": "ok",
  "quercus-blufftonensis.html": "ok",
  "quercus-borosii.html": "ok",
  "quercus-bourgaei.html": "ok",
  "quercus-boweniana.html": "ok",
  "quercus-boyntonii.html": "ok",
  "quercus-braianensis.html": "ok",
  "quercus-brandegeei.html": "ok",
  "quercus-brandisiana.html": "ok",
  "quercus-brantii.html": "ok",
  "quercus-breedloveana.html": "ok",
  "quercus-brenesii.html": "ok",
  "quercus-brevicalyx.html": "ok",
  "quercus-breviradiata.html": "ok",
  "quercus-brittonii.html": "ok",
  "quercus-browni.html": "ok",
  "quercus-buckleyi.html": "ok",
  "quercus-burnetensis.html": "ok",
  "quercus-bushii.html": "ok",
  "quercus-caduca.html": "ok",
  "quercus-calophylla.html": "ok",
  "quercus-cambodiensis.html": "ok",
  "quercus-campitica.html": "ok",
  "quercus-camusiae.html": "ok",
  "quercus-canariensis.html": "ok",
  "quercus-canbyi.html": "ok",
  "quercus-cantabrica.html": "ok",
  "quercus-capesii.html": "ok",
  "quercus-carbonensis.html": "ok",
  "quercus-carduchorum.html": "ok",
  "quercus-carmenensis.html": "ok",
  "quercus-carolinensis.html": "ok",
  "quercus-carrissoana.html": "ok",
  "quercus-castanea.html": "ok",
  "quercus-castaneifolia.html": "ok",
  "quercus-castaneopsis.html": "ok",
  "quercus-castanopseifolia.html": "ok",
  "quercus-catesbaeifolia.html": "ok",
  "quercus-cedrosensis.html": "ok",
  "quercus-centenaria.html": "ok",
  "quercus-cerrioides.html": "ok",
  "quercus-cerris.html": "ok",
  "quercus-cerris-x-quercus-petraea.html": "ok",
  "quercus-chamissonis.html": "ok",
  "quercus-championii.html": "ok",
  "quercus-chaneyi.html": "ok",
  "quercus-chapmanii.html": "ok",
  "quercus-charcasana.html": "ok",
  "quercus-chartacea.html": "ok",
  "quercus-chenii.html": "ok",
  "quercus-chevalieri.html": "ok",
  "quercus-chiapensis.html": "ok",
  "quercus-chihuahuensis.html": "ok",
  "quercus-chimaltenangana.html": "ok",
  "quercus-chrysocalyx.html": "ok",
  "quercus-chrysolepis.html": "ok",
  "quercus-chrysotricha.html": "ok",
  "quercus-chungii.html": "ok",
  "quercus-ciliaris.html": "ok",
  "quercus-clarnensis.html": "ok",
  "quercus-clementei.html": "ok",
  "quercus-coahuilensis.html": "ok",
  "quercus-coccifera.html": "ok",
  "quercus-cocciferoides.html": "ok",
  "quercus-coccinea.html": "ok",
  "quercus-cocksii.html": "ok",
  "quercus-coffeaecolor.html": "ok",
  "quercus-coffeicolor.html": "ok",
  "quercus-cognatus.html": "ok",
  "quercus-collettii.html": "ok",
  "quercus-columnaris.html": "ok",
  "quercus-comptoniae.html": "ok",
  "quercus-conduplicans.html": "ok",
  "quercus-conferta.html": "ok",
  "quercus-confertifolia.html": "ok",
  "quercus-congesta.html": "ok",
  "quercus-conjungens.html": "ok",
  "quercus-consanguinea.html": "ok",
  "quercus-convallata.html": "ok",
  "quercus-convexa.html": "ok",
  "quercus-conzattii.html": "ok",
  "quercus-copeyensis.html": "ok",
  "quercus-coriacea.html": "ok",
  "quercus-cornelius-muelleri.html": "ok",
  "quercus-cornelius-mulleri.html": "ok",
  "quercus-corrugata.html": "ok",
  "quercus-cortesii.html": "ok",
  "quercus-costaricensis.html": "ok",
  "quercus-coutinhoi.html": "ok",
  "quercus-crassifolia.html": "ok",
  "quercus-crassipes.html": "ok",
  "quercus-cravenensis.html": "ok",
  "quercus-crenata.html": "ok",
  "quercus-crispifolia.html": "ok",
  "quercus-crispipilis.html": "ok",
  "quercus-crispula.html": "ok",
  "quercus-crossii.html": "ok",
  "quercus-cualensis.html": "ok",
  "quercus-culveri.html": "ok",
  "quercus-dacica.html": "ok",
  "quercus-daimingshanensis.html": "ok",
  "quercus-dakotensis.html": "ok",
  "quercus-dalechampii.html": "ok",
  "quercus-dallii.html": "ok",
  "quercus-dawsonii.html": "ok",
  "quercus-dayana.html": "ok",
  "quercus-deamii.html": "ok",
  "quercus-decipiens.html": "ok",
  "quercus-declinata.html": "ok",
  "quercus-delavayi.html": "ok",
  "quercus-deleiensis.html": "ok",
  "quercus-delicatula.html": "ok",
  "quercus-deliquescens.html": "ok",
  "quercus-demareei.html": "ok",
  "quercus-densifolia.html": "ok",
  "quercus-dentata.html": "ok",
  "quercus-dentoni.html": "ok",
  "quercus-dentosa.html": "ok",
  "quercus-depressa.html": "ok",
  "quercus-depressipes.html": "ok",
  "quercus-deserticola.html": "ok",
  "quercus-dilacerata.html": "ok",
  "quercus-dilatata.html": "ok",
  "quercus-dinghuensis.html": "ok",
  "quercus-disciformis.html": "ok",
  "quercus-discreta.html": "ok",
  "quercus-distincta.html": "ok",
  "quercus-diversifolia.html": "ok",
  "quercus-diversiloba.html": "ok",
  "quercus-dolicholepis.html": "ok",
  "quercus-doljensis.html": "ok",
  "quercus-donnaiensis.html": "ok",
  "quercus-douglasii.html": "ok",
  "quercus-drummondii.html": "ok",
  "quercus-drymeja.html": "ok",
  "quercus-dryophyllopsis.html": "ok",
  "quercus-dschorochensis.html": "ok",
  "quercus-dubia.html": "ok",
  "quercus-dumosa.html": "ok",
  "quercus-durata.html": "ok",
  "quercus-durifolia.html": "ok",
  "quercus-duriuscula.html": "ok",
  "quercus-dysophylla.html": "ok",
  "quercus-eamesi.html": "ok",
  "quercus-edithae.html": "ok",
  "quercus-edithiae.html": "ok",
  "quercus-eduardi.html": "ok",
  "quercus-edwardsae.html": "ok",
  "quercus-edwardsiae.html": "ok",
  "quercus-egglestonii.html": "ok",
  "quercus-elaena.html": "ok",
  "quercus-elaenoides.html": "ok",
  "quercus-elegans.html": "ok",
  "quercus-elevaticostata.html": "ok",
  "quercus-ellipsoidalis.html": "ok",
  "quercus-elliptica.html": "ok",
  "quercus-ellisiana.html": "ok",
  "quercus-ellsworthianus.html": "ok",
  "quercus-elmeri.html": "ok",
  "quercus-elongata.html": "ok",
  "quercus-elwyni.html": "ok",
  "quercus-emoryi.html": "ok",
  "quercus-engelmannii.html": "ok",
  "quercus-engleriana.html": "ok",
  "quercus-eoxalapensis.html": "ok",
  "quercus-estremadurensis.html": "ok",
  "quercus-eumorpha.html": "ok",
  "quercus-ewanii.html": "ok",
  "quercus-exacta.html": "ok",
  "quercus-fabrei.html": "ok",
  "quercus-faginea.html": "ok",
  "quercus-falcata.html": "ok",
  "quercus-fangshanensis.html": "ok",
  "quercus-faxonii.html": "ok",
  "quercus-fenestrata.html": "ok",
  "quercus-fernaldii.html": "ok",
  "quercus-filialis.html": "ok",
  "quercus-fimbriata.html": "ok",
  "quercus-firmurensis.html": "ok",
  "quercus-fisheriana.html": "ok",
  "quercus-floccosa.html": "ok",
  "quercus-flocculenta.html": "ok",
  "quercus-floribunda.html": "ok",
  "quercus-fontana.html": "ok",
  "quercus-fontanesii.html": "ok",
  "quercus-fontqueri.html": "ok",
  "quercus-franchetii.html": "ok",
  "quercus-fraxinifolia.html": "ok",
  "quercus-frutex.html": "ok",
  "quercus-fulva.html": "ok",
  "quercus-furcinervis.html": "ok",
  "quercus-furfuracea.html": "ok",
  "quercus-furuhjelmi.html": "ok",
  "quercus-fusiformis.html": "ok",
  "quercus-gaharuensis.html": "ok",
  "quercus-galeanensis.html": "ok",
  "quercus-gallaecica.html": "ok",
  "quercus-gambelii.html": "ok",
  "quercus-gambleana.html": "ok",
  "quercus-ganderi.html": "ok",
  "quercus-garlandensis.html": "ok",
  "quercus-garryana.html": "ok",
  "quercus-gaudini.html": "ok",
  "quercus-gemelliflora.html": "ok",
  "quercus-geminata.html": "ok",
  "quercus-georgiana.html": "ok",
  "quercus-germana.html": "ok",
  "quercus-ghiesbreghtii.html": "ok",
  "quercus-giffordii.html": "ok",
  "quercus-gilbertii.html": "ok",
  "quercus-gilva.html": "ok",
  "quercus-glabrescens.html": "ok",
  "quercus-glauca.html": "ok",
  "quercus-glaucescens.html": "ok",
  "quercus-glaucoides.html": "ok",
  "quercus-glomerata.html": "ok",
  "quercus-godeti.html": "ok",
  "quercus-goepperti.html": "ok",
  "quercus-gomeziana.html": "ok",
  "quercus-gracilenta.html": "ok",
  "quercus-grahamii.html": "ok",
  "quercus-gravesii.html": "ok",
  "quercus-greeneana.html": "ok",
  "quercus-greggii.html": "ok",
  "quercus-griffithii.html": "ok",
  "quercus-grisea.html": "ok",
  "quercus-groenlandica.html": "ok",
  "quercus-grossidentata.html": "ok",
  "quercus-guadalupensis.html": "ok",
  "quercus-guayabalana.html": "ok",
  "quercus-guyavifolia.html": "ok",
  "quercus-handeliana.html": "ok",
  "quercus-harbisonii.html": "ok",
  "quercus-hartwissiana.html": "ok",
  "quercus-hastingsii.html": "ok",
  "quercus-hatcheri.html": "ok",
  "quercus-haugi.html": "ok",
  "quercus-havardii.html": "ok",
  "quercus-hawkinsiae.html": "ok",
  "quercus-hawkinsii.html": "ok",
  "quercus-haydeni.html": "ok",
  "quercus-haynaldiana.html": "ok",
  "quercus-helferiana.html": "ok",
  "quercus-helvetica.html": "ok",
  "quercus-hemisphaerica.html": "ok",
  "quercus-hesperia.html": "ok",
  "quercus-heterophylla.html": "ok",
  "quercus-hexagona.html": "ok",
  "quercus-hieracifolia.html": "ok",
  "quercus-hillii.html": "ok",
  "quercus-hinckleyi.html": "ok",
  "quercus-hintonii.html": "ok",
  "quercus-hintoniorum.html": "ok",
  "quercus-hirtifolia.html": "ok",
  "quercus-hispanica.html": "ok",
  "quercus-hollickii.html": "ok",
  "quercus-holmesii.html": "ok",
  "quercus-honbaensis.html": "ok",
  "quercus-hondae.html": "ok",
  "quercus-hopeiensis.html": "ok",
  "quercus-horniana.html": "ok",
  "quercus-hosiana.html": "ok",
  "quercus-howellii.html": "ok",
  "quercus-hui.html": "ok",
  "quercus-huicholensis.html": "ok",
  "quercus-humboldtii.html": "ok",
  "quercus-humidicola.html": "ok",
  "quercus-hybr.html": "ok",
  "quercus-hypargyrea.html": "ok",
  "quercus-hypoleucoides.html": "ok",
  "quercus-hypophaea.html": "ok",
  "quercus-hypoxantha.html": "ok",
  "quercus-idahoensis.html": "ok",
  "quercus-idzuensis.html": "ok",
  "quercus-ilex.html": "ok",
  "quercus-ilicifolia.html": "ok",
  "quercus-iltisii.html": "ok",
  "quercus-imbricaria.html": "ok",
  "quercus-imbricariaefolia.html": "ok",
  "quercus-incana.html": "ok",
  "quercus-incomita.html": "ok",
  "quercus-inconstans.html": "ok",
  "quercus-inermis.html": "ok",
  "quercus-infectoria.html": "ok",
  "quercus-inopina.html": "ok",
  "quercus-insignis.html": "ok",
  "quercus-intricata.html": "ok",
  "quercus-introgressa.html": "ok",
  "quercus-invaginata.html": "ok",
  "quercus-ithaburensis.html": "ok",
  "quercus-jackiana.html": "ok",
  "quercus-jahnii.html": "ok",
  "quercus-jenseniana.html": "ok",
  "quercus-john-tuckeri.html": "ok",
  "quercus-johnstrupi.html": "ok",
  "quercus-jolonensis.html": "ok",
  "quercus-jonesii.html": "ok",
  "quercus-joorii.html": "ok",
  "quercus-judithae.html": "ok",
  "quercus-kelloggii.html": "ok",
  "quercus-kerneri.html": "ok",
  "quercus-kerrii.html": "ok",
  "quercus-kewensis.html": "ok",
  "quercus-kinseliae.html": "ok",
  "quercus-kiukiangensis.html": "ok",
  "quercus-knoblochii.html": "ok",
  "quercus-knowltoniana.html": "ok",
  "quercus-kotschyana.html": "ok",
  "quercus-kouangsiensis.html": "ok",
  "quercus-l.html": "ok",
  "quercus-laceyi.html": "ok",
  "quercus-laeta.html": "ok",
  "quercus-laevis.html": "ok",
  "quercus-lambertensis.html": "ok",
  "quercus-lamellosa.html": "ok",
  "quercus-lanata.html": "ok",
  "quercus-lanceaefolia.html": "ok",
  "quercus-lancifolia.html": "ok",
  "quercus-langbianensis.html": "ok",
  "quercus-latifolia.html": "ok",
  "quercus-laurifolia.html": "ok",
  "quercus-laurina.html": "ok",
  "quercus-leana.html": "ok",
  "quercus-lehmani.html": "ok",
  "quercus-lenticellata.html": "ok",
  "quercus-lesquereuxiana.html": "ok",
  "quercus-leucotrichophora.html": "ok",
  "quercus-liaoi.html": "ok",
  "quercus-libanerris.html": "ok",
  "quercus-libani.html": "ok",
  "quercus-liboensis.html": "ok",
  "quercus-liebmannii.html": "ok",
  "quercus-lineata.html": "ok",
  "quercus-litseoides.html": "ok",
  "quercus-lobata.html": "ok",
  "quercus-lobbii.html": "ok",
  "quercus-lobulata.html": "ok",
  "quercus-lodicosa.html": "ok",
  "quercus-lonchitis.html": "ok",
  "quercus-longinux.html": "ok",
  "quercus-longispica.html": "ok",
  "quercus-lousae.html": "ok",
  "quercus-lowii.html": "ok",
  "quercus-lucana.html": "ok",
  "quercus-ludoviciana.html": "ok",
  "quercus-lungmaiensis.html": "ok",
  "quercus-lusitanica.html": "ok",
  "quercus-lyrata.html": "ok",
  "quercus-lyratiformis.html": "ok",
  "quercus-maccormickoserrata.html": "ok",
  "quercus-macdanielii.html": "ok",
  "quercus-macdonaldii.html": "ok",
  "quercus-macdougallii.html": "ok",
  "quercus-macnabiana.html": "ok",
  "quercus-macneilii.html": "ok",
  "quercus-macranthera.html": "ok",
  "quercus-macrocalyx.html": "ok",
  "quercus-macrocarpa.html": "ok",
  "quercus-macvaughii.html": "ok",
  "quercus-magnoliifolia.html": "ok",
  "quercus-magnosquamata.html": "ok",
  "quercus-mannifera.html": "ok",
  "quercus-manzanillana.html": "ok",
  "quercus-margaretiae.html": "ok",
  "quercus-margaretta.html": "ok",
  "quercus-margarettae.html": "ok",
  "quercus-marilandica.html": "ok",
  "quercus-marlipoensis.html": "ok",
  "quercus-mas.html": "ok",
  "quercus-mccormickii.html": "ok",
  "quercus-mcvaughii.html": "ok",
  "quercus-megaleia.html": "ok",
  "quercus-melissae.html": "ok",
  "quercus-mellichampii.html": "ok",
  "quercus-merriami.html": "ok",
  "quercus-merrillii.html": "ok",
  "quercus-mespilifolia.html": "ok",
  "quercus-mexiae.html": "ok",
  "quercus-mexicana.html": "ok",
  "quercus-michauxii.html": "ok",
  "quercus-microdentata.html": "ok",
  "quercus-microphylla.html": "ok",
  "quercus-milleri.html": "ok",
  "quercus-minima.html": "ok",
  "quercus-minor.html": "ok",
  "quercus-miovariabilis.html": "ok",
  "quercus-miyagii.html": "ok",
  "quercus-mohriana.html": "ok",
  "quercus-mongolica.html": "ok",
  "quercus-mongolicodentata.html": "ok",
  "quercus-mongolika.html": "ok",
  "quercus-monimotricha.html": "ok",
  "quercus-monnula.html": "ok",
  "quercus-montana.html": "ok",
  "quercus-montanensis.html": "ok",
  "quercus-morehus.html": "ok",
  "quercus-morii.html": "ok",
  "quercus-morisii.html": "ok",
  "quercus-morrisoniana.html": "ok",
  "quercus-motuoensis.html": "ok",
  "quercus-moultonensis.html": "ok",
  "quercus-mudgii.html": "ok",
  "quercus-muehlenbergii.html": "ok",
  "quercus-mulleri.html": "ok",
  "quercus-multinervis.html": "ok",
  "quercus-munzii.html": "ok",
  "quercus-mutabilis.html": "ok",
  "quercus-myrsinaefolia.html": "ok",
  "quercus-myrsinifolia.html": "ok",
  "quercus-myrtifolia.html": "ok",
  "quercus-nanchuanica.html": "ok",
  "quercus-negundoides.html": "ok",
  "quercus-neomairei.html": "ok",
  "quercus-neomexicana.html": "ok",
  "quercus-neopalmeri.html": "ok",
  "quercus-neotharpii.html": "ok",
  "quercus-nessiana.html": "ok",
  "quercus-nevadensis.html": "ok",
  "quercus-ngochoaensis.html": "ok",
  "quercus-nigra.html": "ok",
  "quercus-nigrescens.html": "ok",
  "quercus-ningangensis.html": "ok",
  "quercus-nipponica.html": "ok",
  "quercus-nivea.html": "ok",
  "quercus-novaecaesareae.html": "ok",
  "quercus-novagrenobii.html": "ok",
  "quercus-numantina.html": "ok",
  "quercus-obconicus.html": "ok",
  "quercus-oblongifolia.html": "ok",
  "quercus-obtusa.html": "ok",
  "quercus-obtusanthera.html": "ok",
  "quercus-obtusata.html": "ok",
  "quercus-obtusifolia.html": "ok",
  "quercus-ocoteaefolia.html": "ok",
  "quercus-oglethorpensis.html": "ok",
  "quercus-oidocarpa.html": "ok",
  "quercus-olafseni.html": "ok",
  "quercus-oleoides.html": "ok",
  "quercus-oocarpa.html": "ok",
  "quercus-opaca.html": "ok",
  "quercus-ophiosquamata.html": "ok",
  "quercus-organensis.html": "ok",
  "quercus-oviedoensis.html": "ok",
  "quercus-oxyodon.html": "ok",
  "quercus-oxyphylla.html": "ok",
  "quercus-pachucana.html": "ok",
  "quercus-pachyloma.html": "ok",
  "quercus-pacifica.html": "ok",
  "quercus-pagoda.html": "ok",
  "quercus-pagodaefolia.html": "ok",
  "quercus-palaeolithicola.html": "ok",
  "quercus-palmeri.html": "ok",
  "quercus-palmeriana.html": "ok",
  "quercus-paludosa.html": "ok",
  "quercus-palustris.html": "ok",
  "quercus-palustris-x-rubra.html": "ok",
  "quercus-panamandinaea.html": "ok",
  "quercus-pannosa.html": "ok",
  "quercus-parceserrata.html": "ok",
  "quercus-parvula.html": "ok",
  "quercus-pastorensis.html": "ok",
  "quercus-paucidentata.html": "ok",
  "quercus-pauciradiata.html": "ok",
  "quercus-paui.html": "ok",
  "quercus-paxtalensis.html": "ok",
  "quercus-payettensis.html": "ok",
  "quercus-peduncularis.html": "ok",
  "quercus-pedunculata.html": "ok",
  "quercus-penasii.html": "ok",
  "quercus-penhallowi.html": "ok",
  "quercus-peninsularis.html": "ok",
  "quercus-pennivenia.html": "ok",
  "quercus-pentacycla.html": "ok",
  "quercus-percoriacea.html": "ok",
  "quercus-peritula.html": "ok",
  "quercus-perpallida.html": "ok",
  "quercus-perseaefolia.html": "ok",
  "quercus-persica.html": "ok",
  "quercus-petraea.html": "ok",
  "quercus-petraea-x-pubescens.html": "ok",
  "quercus-petraea-x-robur.html": "ok",
  "quercus-phanera.html": "ok",
  "quercus-phellos.html": "ok",
  "quercus-phillyraeoides.html": "ok",
  "quercus-phillyreoides.html": "ok",
  "quercus-phillyrioides.html": "ok",
  "quercus-pinbianensis.html": "ok",
  "quercus-pinnatifida.html": "ok",
  "quercus-pinnativenulosa.html": "ok",
  "quercus-planipocula.html": "ok",
  "quercus-platanoides.html": "ok",
  "quercus-platycalyx.html": "ok",
  "quercus-pliopalmeri.html": "ok",
  "quercus-poilanei.html": "ok",
  "quercus-polymorpha.html": "ok",
  "quercus-pongtungensis.html": "ok",
  "quercus-pontica.html": "ok",
  "quercus-porphyrogenita.html": "ok",
  "quercus-potosina.html": "ok",
  "quercus-praeco.html": "ok",
  "quercus-praegilva.html": "ok",
  "quercus-praenigra.html": "ok",
  "quercus-prasina.html": "ok",
  "quercus-pratti.html": "ok",
  "quercus-previrginiana.html": "ok",
  "quercus-primordialis.html": "ok",
  "quercus-pringlei.html": "ok",
  "quercus-prinoides.html": "ok",
  "quercus-protosalicina.html": "ok",
  "quercus-pseudinfectoria.html": "ok",
  "quercus-pseudoalba.html": "ok",
  "quercus-pseudoalnus.html": "ok",
  "quercus-pseudocastanea.html": "ok",
  "quercus-pseudocerris.html": "ok",
  "quercus-pseudococcifera.html": "ok",
  "quercus-pseudocornea.html": "ok",
  "quercus-pseudodalechampii.html": "ok",
  "quercus-pseudodchorochensis.html": "ok",
  "quercus-pseudolyrata.html": "ok",
  "quercus-pseudomargaretta.html": "ok",
  "quercus-pseudomyrsinaefolia.html": "ok",
  "quercus-pseudosemicarpifolia.html": "ok",
  "quercus-pseudoverticillata.html": "ok",
  "quercus-pseudowestfalica.html": "ok",
  "quercus-pubens.html": "ok",
  "quercus-pubescens.html": "ok",
  "quercus-pubescens-x-robur.html": "ok",
  "quercus-puentei.html": "ok",
  "quercus-pumila.html": "ok",
  "quercus-pungens.html": "ok",
  "quercus-purulhana.html": "ok",
  "quercus-pyrenaica.html": "ok",
  "quercus-quangtriensis.html": "ok",
  "quercus-radiata.html": "ok",
  "quercus-raineri.html": "ok",
  "quercus-ramaleyi.html": "ok",
  "quercus-ramsbottomii.html": "ok",
  "quercus-ratonensis.html": "ok",
  "quercus-reflexa.html": "ok",
  "quercus-rehderi.html": "ok",
  "quercus-rehderiana.html": "ok",
  "quercus-rekonis.html": "ok",
  "quercus-repanda.html": "ok",
  "quercus-resinosa.html": "ok",
  "quercus-rex.html": "ok",
  "quercus-rhamnoides.html": "ok",
  "quercus-rhodopea.html": "ok",
  "quercus-richteri.html": "ok",
  "quercus-rineharticena.html": "ok",
  "quercus-riparia.html": "ok",
  "quercus-robbinsii.html": "ok",
  "quercus-robur.html": "ok",
  "quercus-robur-x-quercus-rubra.html": "ok",
  "quercus-rolfsii.html": "ok",
  "quercus-rosa-pintii.html": "ok",
  "quercus-rosacea.html": "ok",
  "quercus-rotundifolia.html": "ok",
  "quercus-rubra.html": "ok",
  "quercus-rubramenta.html": "ok",
  "quercus-rudkinii.html": "ok",
  "quercus-rugosa.html": "ok",
  "quercus-runcinata.html": "ok",
  "quercus-runcinatifolia.html": "ok",
  "quercus-rupestris.html": "ok",
  "quercus-rustii.html": "ok",
  "quercus-rysophylla.html": "ok",
  "quercus-sadleriana.html": "ok",
  "quercus-saei.html": "ok",
  "quercus-sagraeana.html": "ok",
  "quercus-sagrana.html": "ok",
  "quercus-salcedoi.html": "ok",
  "quercus-salicifolia.html": "ok",
  "quercus-salicina.html": "ok",
  "quercus-saltillensis.html": "ok",
  "quercus-salvadorensis.html": "ok",
  "quercus-salzmanniana.html": "ok",
  "quercus-sanchezcolinii.html": "ok",
  "quercus-sapotifolia.html": "ok",
  "quercus-sarahmariae.html": "ok",
  "quercus-saravanensis.html": "ok",
  "quercus-sargentii.html": "ok",
  "quercus-sartorii.html": "ok",
  "quercus-saulii.html": "ok",
  "quercus-schochiana.html": "ok",
  "quercus-schottkyana.html": "ok",
  "quercus-scudderi.html": "ok",
  "quercus-scytophylla.html": "ok",
  "quercus-sebifera.html": "ok",
  "quercus-seemannii.html": "ok",
  "quercus-segoviensis.html": "ok",
  "quercus-semecarpifolia.html": "ok",
  "quercus-semiserrata.html": "ok",
  "quercus-semiserratoides.html": "ok",
  "quercus-senescens.html": "ok",
  "quercus-senneniana.html": "ok",
  "quercus-serra.html": "ok",
  "quercus-serrata.html": "ok",
  "quercus-sessilifolia.html": "ok",
  "quercus-setulosa.html": "ok",
  "quercus-shennongii.html": "ok",
  "quercus-shingjenensis.html": "ok",
  "quercus-shumardii.html": "ok",
  "quercus-sichourensis.html": "ok",
  "quercus-sicula.html": "ok",
  "quercus-sideroxyla.html": "ok",
  "quercus-similis.html": "ok",
  "quercus-simplex.html": "ok",
  "quercus-simulata.html": "ok",
  "quercus-sinuata.html": "ok",
  "quercus-skinneri.html": "ok",
  "quercus-sororia.html": "ok",
  "quercus-spinosa.html": "ok",
  "quercus-spurioilex.html": "ok",
  "quercus-stantoni.html": "ok",
  "quercus-steenisii.html": "ok",
  "quercus-steenstrupiana.html": "ok",
  "quercus-stellata.html": "ok",
  "quercus-stenophylloides.html": "ok",
  "quercus-sterilis.html": "ok",
  "quercus-sterrettii.html": "ok",
  "quercus-stewardiana.html": "ok",
  "quercus-stramineus.html": "ok",
  "quercus-streimii.html": "ok",
  "quercus-striatula.html": "ok",
  "quercus-subconvexa.html": "ok",
  "quercus-suber.html": "ok",
  "quercus-suberoides.html": "ok",
  "quercus-subfalcata.html": "ok",
  "quercus-subglaucescens.html": "ok",
  "quercus-subintegra.html": "ok",
  "quercus-suboccolta.html": "ok",
  "quercus-subsericea.html": "ok",
  "quercus-subspathulata.html": "ok",
  "quercus-substellata.html": "ok",
  "quercus-subvariabilis.html": "ok",
  "quercus-succulenta.html": "ok",
  "quercus-sullyi.html": "ok",
  "quercus-sumatrana.html": "ok",
  "quercus-sumterensis.html": "ok",
  "quercus-supranitida.html": "ok",
  "quercus-suspecta.html": "ok",
  "quercus-tabajdiana.html": "ok",
  "quercus-takatorensis.html": "ok",
  "quercus-tarahumara.html": "ok",
  "quercus-tardifolia.html": "ok",
  "quercus-tarokoensis.html": "ok",
  "quercus-texana.html": "ok",
  "quercus-tharpii.html": "ok",
  "quercus-thorelii.html": "ok",
  "quercus-tiaoloshanica.html": "ok",
  "quercus-tingitana.html": "ok",
  "quercus-tinkhamii.html": "ok",
  "quercus-tlemcenensis.html": "ok",
  "quercus-tomentella.html": "ok",
  "quercus-tomentosinervis.html": "ok",
  "quercus-tonduzii.html": "ok",
  "quercus-toumeyi.html": "ok",
  "quercus-townei.html": "ok",
  "quercus-toxicodendrifolia.html": "ok",
  "quercus-toza.html": "ok",
  "quercus-trabutii.html": "ok",
  "quercus-transiens.html": "ok",
  "quercus-treubiana.html": "ok",
  "quercus-tridentata.html": "ok",
  "quercus-trojana.html": "ok",
  "quercus-trungkhanhensis.html": "ok",
  "quercus-tsinglingensis.html": "ok",
  "quercus-tuberculata.html": "ok",
  "quercus-tuitensis.html": "ok",
  "quercus-tungmaiensis.html": "ok",
  "quercus-turbinella.html": "ok",
  "quercus-turneri.html": "ok",
  "quercus-undulata.html": "ok",
  "quercus-ungeri.html": "ok",
  "quercus-urbani.html": "ok",
  "quercus-urticifolia.html": "ok",
  "quercus-utilis.html": "ok",
  "quercus-uxoris.html": "ok",
  "quercus-vacciniifolia.html": "ok",
  "quercus-vaga.html": "ok",
  "quercus-valdensis.html": "ok",
  "quercus-valdinervosa.html": "ok",
  "quercus-variabilis.html": "ok",
  "quercus-vaseyana.html": "ok",
  "quercus-velutina.html": "ok",
  "quercus-venulosa.html": "ok",
  "quercus-verde.html": "ok",
  "quercus-vertesiensis.html": "ok",
  "quercus-viburnifolia.html": "ok",
  "quercus-vicentensis.html": "ok",
  "quercus-viminea.html": "ok",
  "quercus-virginiana.html": "ok",
  "quercus-viridis.html": "ok",
  "quercus-viveri.html": "ok",
  "quercus-voyana.html": "ok",
  "quercus-vulcanica.html": "ok",
  "quercus-wagneri.html": "ok",
  "quercus-walteriana.html": "ok",
  "quercus-warburgii.html": "ok",
  "quercus-wardiana.html": "ok",
  "quercus-warei.html": "ok",
  "quercus-washingtonensis.html": "ok",
  "quercus-weedii.html": "ok",
  "quercus-welshii.html": "ok",
  "quercus-whitei.html": "ok",
  "quercus-willdenowiana.html": "ok",
  "quercus-wislizeni.html": "ok",
  "quercus-wutaishanica.html": "ok",
  "quercus-xalapensis.html": "ok",
  "quercus-xanthoclada.html": "ok",
  "quercus-xanthotricha.html": "ok",
  "quercus-xuanlienensis.html": "ok",
  "quercus-xylina.html": "ok",
  "quercus-yanceyi.html": "ok",
  "quercus-yiwuensis.html": "ok",
  "quercus-yokohamensis.html": "ok",
  "quercus-yongchunana.html": "ok",
  "quercus-yulensis.html": "ok",
  "quereuxia-angulata.html": "ok",
  "queria-chilensis.html": "ok",
  "quesnelia-alborosea.html": "ok",
  "quesnelia-alvimii.html": "ok",
  "quesnelia-arvensis.html": "ok",
  "quesnelia-augustocoburgi.html": "ok",
  "quesnelia-blanda.html": "ok",
  "quesnelia-clavata.html": "ok",
  "quesnelia-conquistensis.html": "ok",
  "quesnelia-dubia.html": "ok",
  "quesnelia-edmundoi.html": "ok",
  "quesnelia-gaudich.html": "ok",
  "quesnelia-georgiizizkae.html": "ok",
  "quesnelia-humilis.html": "ok",
  "quesnelia-imbricata.html": "ok",
  "quesnelia-indecora.html": "ok",
  "quesnelia-koltesii.html": "ok",
  "quesnelia-lateralis.html": "ok",
  "quesnelia-liboniana.html": "ok",
  "quesnelia-marmorata.html": "ok",
  "quesnelia-morreniana.html": "ok",
  "quesnelia-quesneliana.html": "ok",
  "quesnelia-skinneri.html": "ok",
  "quesnelia-strobilispica.html": "ok",
  "quesnelia-testudo.html": "ok",
  "quesnelia-tubifolia.html": "ok",
  "quesnelia-vasconcelosiana.html": "ok",
  "quesnelia-violacea.html": "ok",
  "quetzalia-areolata.html": "ok",
  "quetzalia-contracta.html": "ok",
  "quetzalia-ilicina.html": "ok",
  "quetzalia-lundell.html": "ok",
  "quetzalia-occidentalis.html": "ok",
  "quetzalia-pauciflora.html": "ok",
  "quetzalia-schiedeana.html": "ok",
  "quetzalia-stipitata.html": "ok",
  "quezeliantha-tibestica.html": "ok",
  "quiabentia-verticillata.html": "ok",
  "quiabentia-zehntneri.html": "ok",
  "quiina-amazonica.html": "ok",
  "quiina-attenuata.html": "ok",
  "quiina-aubl.html": "ok",
  "quiina-berryi.html": "ok",
  "quiina-cruegeriana.html": "ok",
  "quiina-decastyla.html": "ok",
  "quiina-florida.html": "ok",
  "quiina-gentryi.html": "ok",
  "quiina-glaziouvii.html": "ok",
  "quiina-glaziovii.html": "ok",
  "quiina-grandifolia.html": "ok",
  "quiina-guianensis.html": "ok",
  "quiina-integrifolia.html": "ok",
  "quiina-jamaicensis.html": "ok",
  "quiina-longifolia.html": "ok",
  "quiina-macrophylla.html": "ok",
  "quiina-magellano-gomezii.html": "ok",
  "quiina-maguirei.html": "ok",
  "quiina-negrensis.html": "ok",
  "quiina-obovata.html": "ok",
  "quiina-oiapocensis.html": "ok",
  "quiina-paraensis.html": "ok",
  "quiina-parvifolia.html": "ok",
  "quiina-pteridophylla.html": "ok",
  "quiina-rhytidopus.html": "ok",
  "quiina-sessilis.html": "ok",
  "quiina-tinifolia.html": "ok",
  "quiina-wurdackii.html": "ok",
  "quiina-yatuensis.html": "ok",
  "quiinaceae.html": "ok",
  "quillaja-brasiliensis.html": "ok",
  "quillaja-molina.html": "ok",
  "quillaja-saponaria.html": "ok",
  "quillaja-smegmadermis.html": "ok",
  "quinaria-raf.html": "ok",
  "quinchamala-willd.html": "ok",
  "quinchamalium-araucanum.html": "ok",
  "quinchamalium-chilense.html": "ok",
  "quinchamalium-juss-1789.html": "ok",
  "quinchamalium-linifolium.html": "ok",
  "quincula-lobata.html": "ok",
  "quincula-raf.html": "ok",
  "quinetia-urvillei.html": "ok",
  "quinqueremulus-linearis.html": "ok",
  "quinquina-boehm.html": "ok",
  "quintinia-adc.html": "ok",
  "quintinia-acutifolia.html": "ok",
  "quintinia-apoensis.html": "ok",
  "quintinia-brassii.html": "ok",
  "quintinia-elliptica.html": "ok",
  "quintinia-epiphytica.html": "ok",
  "quintinia-fawkneri.html": "ok",
  "quintinia-hyehenensis.html": "ok",
  "quintinia-kuborensis.html": "ok",
  "quintinia-lanceolata.html": "ok",
  "quintinia-ledermannii.html": "ok",
  "quintinia-macgregorii.html": "ok",
  "quintinia-macrophylla.html": "ok",
  "quintinia-major.html": "ok",
  "quintinia-media.html": "ok",
  "quintinia-minor.html": "ok",
  "quintinia-montiswilhelmii.html": "ok",
  "quintinia-nutantiflora.html": "ok",
  "quintinia-nutantifora.html": "ok",
  "quintinia-oreophila.html": "ok",
  "quintinia-quatrefagesii.html": "ok",
  "quintinia-rigida.html": "ok",
  "quintinia-schlechteriana.html": "ok",
  "quintinia-sieberi.html": "ok",
  "quintinia-tasmanensis.html": "ok",
  "quintinia-verdonii.html": "ok",
  "quintiniapollis-dcmildenhall-dtpocknall-1989.html": "ok",
  "quintiniapollis-striatulosa.html": "ok",
  "quiotania-amazonica.html": "ok",
  "quipuanthus-epipetricus.html": "ok",
  "quisqualis-l.html": "ok",
  "quisqueya-dod.html": "ok",
  "quisqueya-ekmanii.html": "ok",
  "quisqueya-holdridgei.html": "ok",
  "quisqueya-karstii.html": "ok",
  "quisqueya-rosea.html": "ok",
  "quivisia-comm-ex-juss.html": "ok",
  "quivisianthe-baill.html": "ok",
  "quivisianthe-papinae.html": "ok",
  "quoya-atriplicina.html": "ok",
  "quoya-cuneata.html": "ok",
  "quoya-dilatata.html": "ok",
  "quoya-loxocarpa.html": "ok",
  "quoya-oldfieldii.html": "ok",
  "quoya-paniculata.html": "ok",
  "quoya-verbascina.html": "ok"
}